eto/__init__.py
eto/core.py
eto/param_est.py
eto/util.py
eto/datasets/__init__.py
eto/datasets/example_daily.csv.zip
eto/datasets/example_daily_results.csv.zip
eto/methods/ETo.py
eto/methods/__init__.py
eto/methods/hargreaves.py
eto/tests/__init__.py
eto/tests/test_eto.py
eto/tests/utest_eto.py
eto-1.1.1.dist-info/METADATA
eto-1.1.1.dist-info/WHEEL
eto-1.1.1.dist-info/licenses/LICENSE.txt
eto-1.1.1.dist-info/RECORD
