Metadata-Version: 2.3
Name: ETo
Version: 1.1.1
Summary: Class and functions to estimate reference ET
Project-URL: Homepage, https://github.com/mullenkamp/ETo
Author-email: Mike Kittridge <mullenkamp1@gmail.com>
License-Expression: Apache-2.0
License-File: LICENSE.txt
Keywords: et,reference
Classifier: Development Status :: 3 - Alpha
Classifier: Intended Audience :: Developers
Classifier: License :: OSI Approved :: Apache Software License
Classifier: Programming Language :: Python :: 2
Classifier: Programming Language :: Python :: 2.7
Classifier: Programming Language :: Python :: 3
Classifier: Programming Language :: Python :: 3.4
Classifier: Programming Language :: Python :: 3.5
Classifier: Programming Language :: Python :: 3.6
Classifier: Topic :: Software Development :: Build Tools
Requires-Python: >=3.8
Requires-Dist: pandas
